zohoapi/__init__.py
zohoapi/api.py
zohoapi/config.py
zohoapi/errors.py
zohoapi-1.0.dist-info/DESCRIPTION.rst
zohoapi-1.0.dist-info/METADATA
zohoapi-1.0.dist-info/RECORD
zohoapi-1.0.dist-info/WHEEL
zohoapi-1.0.dist-info/metadata.json
zohoapi-1.0.dist-info/top_level.txt
