Metadata-Version: 2.0
Name: zohoapi
Version: 1.0
Summary: Wrapper for the Zoho CRM API
Home-page: https://bitbucket.org/cannibalsock/zohoapi
Author: Ben Jarrett
Author-email: UNKNOWN
License: MIT
Keywords: zoho crm
Platform: UNKNOWN
Classifier: Development Status :: 3 - Alpha
Classifier: Programming Language :: Python :: 3.5
Requires-Dist: requests
